{
  "slug": "contact-grounded",
  "title": "Contact-Grounded Policy：具有生成式接触锚定的灵巧视触觉策略",
  "arxiv_id": "2603.05687",
  "url": "https://arxiv.org/abs/2603.05687",
  "category": "机器人操作 · VLA · 策略学习",
  "keywords": [
    "dexterous manipulation",
    "visuotactile policy",
    "contact grounding",
    "diffusion policy",
    "tactile sensing",
    "灵巧操作",
    "接触感知",
    "柔顺控制",
    "多指手",
    "模仿学习"
  ],
  "summary_zh": "CGP 提出通过联合预测机器人实际状态与触觉反馈的耦合轨迹，并借助学习到的接触一致性映射将预测结果转化为柔顺控制器目标，从而在多指灵巧操作中实现显式的多点接触锚定，在仿真与真实机器人任务上均显著超越视触觉 diffusion policy 基线。",
  "date": "2026-06-10",
  "source": "backfill"
}