{
  "slug": "meshflow",
  "title": "MeshFlow: Efficient Artistic Mesh Generation via MeshVAE and Flow-based Diffusion Transformer",
  "arxiv_id": "2606.04621",
  "url": "https://arxiv.org/abs/2606.04621",
  "category": "生成模型 · Generative Models",
  "keywords": ["mesh generation", "MeshVAE", "flow matching", "diffusion transformer", "三维网格生成", "TokenMerge", "rectified flow", "并行生成", "artistic mesh", "point cloud conditioning"],
  "summary_zh": "MeshFlow 提出 MeshVAE（连续隐空间压缩网格几何与拓扑）+ Rectified Flow DiT（并行去噪所有 latent token），约 1.2 秒生成 artist-like 三角网格，比最快 AR 方法快 18 倍，CD/HD 均优于所有 baseline，CVPR 2026 Highlight。",
  "date": "2026-06-14",
  "source": "arxiv-eprint"
}
