{
  "slug": "manigaussian",
  "title": "ManiGaussian: Dynamic Gaussian Splatting for Multi-task Robotic Manipulation",
  "arxiv_id": "2403.08321",
  "url": "https://arxiv.org/abs/2403.08321",
  "category": "机器人 · Robotics",
  "keywords": [
    "robotic manipulation",
    "Gaussian splatting",
    "world model",
    "动态场景建模",
    "多任务学习",
    "语言条件操作",
    "future scene prediction",
    "RLBench",
    "时空动态",
    "scene dynamics"
  ],
  "summary_zh": "ManiGaussian 通过动态 Gaussian Splatting 构建 Gaussian 世界模型，预测机器人操控后的未来场景，以此为监督信号让策略理解场景时空动态，在 RLBench 10 个任务上以 44.8% 平均成功率超越 SOTA 13.1%。",
  "date": "2026-06-10",
  "source": "arxiv-html"
}
