{
  "slug": "lpds",
  "title": "LP-DS: 拉格朗日扰动扩散引导 — 生成策略的潜在空间强化学习",
  "arxiv_id": "2606.01151",
  "url": "https://arxiv.org/abs/2606.01151",
  "category": "机器人 · Robotics",
  "keywords": [
    "扩散策略",
    "强化学习微调",
    "latent space perturbation",
    "Lagrangian trust-region",
    "behavior cloning",
    "flow matching",
    "机器人操控",
    "生成策略",
    "噪声空间引导",
    "模式坍塌"
  ],
  "summary_zh": "LP-DS 通过在冻结扩散/流匹配策略的潜在噪声空间中学习状态条件残差扰动，并以拉格朗日信任域约束防止分布外漂移，实现了轻量级在线强化学习微调，在多个机器人操控基准及真实 Franka 机器人上显著提升了任务成功率。",
  "date": "2026-06-10",
  "source": "backfill"
}